raider_backend/__init__.py
raider_backend/agent_manager.py
raider_backend/connection_managers/agent_manager_connection_manager.py
raider_backend/connection_managers/base_connection_manager.py
raider_backend/connection_managers/launch_connection_manager.py
raider_backend/connection_managers/repo_agent_connection_manager.py
raider_backend/connection_managers/web_raider_connection_manager.py
raider_backend/handlers/agent_manager_handler.py
raider_backend/handlers/base_handler.py
raider_backend/handlers/external_repo_agent_handler.py
raider_backend/launch.py
raider_backend/logger.py
raider_backend/parse.py
raider_backend/planner_agent.py
raider_backend/prompts.py
raider_backend/repo_agents/base_repo_agent.py
raider_backend/repo_agents/external_repo_agent.py
raider_backend/repo_agents/main_repo_agent.py
raider_backend/utils.py
raider_backend-0.0.4.dist-info/METADATA
raider_backend-0.0.4.dist-info/WHEEL
raider_backend-0.0.4.dist-info/entry_points.txt
raider_backend-0.0.4.dist-info/RECORD
