Metadata-Version: 2.1
Name: raider_backend
Version: 0.0.4
Summary: Backend for Raider VS Code Extension
Home-page: https://github.com/sikfeng/raider-backend
Author: Cheong Sik Feng
Author-email: sikfeng@gmail.com
Requires-Python: >=3.10,<3.13
Classifier: Programming Language :: Python :: 3
Classifier: Programming Language :: Python :: 3.10
Classifier: Programming Language :: Python :: 3.11
Classifier: Programming Language :: Python :: 3.12
Requires-Dist: aider-chat (==0.59.0)
Requires-Dist: boto3 (>=1.35.34,<2.0.0)
Requires-Dist: fastapi (>=0.115.0,<0.116.0)
Requires-Dist: litellm (==1.47.0)
Requires-Dist: strictjson (>=5.1.3,<6.0.0)
Requires-Dist: taskgen-ai (>=3.3.4,<4.0.0)
Requires-Dist: uvicorn (>=0.30.6,<0.31.0)
Requires-Dist: web-raider (>=0.0.2,<0.0.3)
Requires-Dist: websockets (>=13.1,<14.0)
Project-URL: Repository, https://github.com/sikfeng/raider-backend
